{
  "title": "slan okus po obmorskih skalah",
  "tags": [
    "poezija"
  ],
  "meta": {
    "index": 1,
    "fileName": "2018-12-26-slan-okus-po-obmorskih-skalah.md",
    "section": "/raztemnenja",
    "dirName": "/articles"
  },
  "date": "2018-12-26",
  "path": "/raztemnenja/slan-okus-po-obmorskih-skalah",
  "permalink": "/raztemnenja/slan-okus-po-obmorskih-skalah",
  "anchors": [],
  "body": "<p>kako se nit razvija<br>\nkako zelo majhen sem <br>\nko vse, kar sva<br>\nz blagim zadržkom<br>\nspustiva iz rok in<br>\nvse, kar sva, postane <br>\nslan okus po obmorskih skalah,<br>\nsintetični dialog in diptih<br>\ntakrat me vprašaš če me je strah bližine<br>\nkdor prej pogleda vstran izgubi<br>\ncel dan lahko te bi<br>\ncel dan <br>\nprebiral <br>\nkaj te je pripeljalo sem<br>\nvsak tvoj gib je <br>\nrazlog da rabim globoko <br>\nzrak<br>\nin jasno je<br>\nkako se nit razvija<br>\nvse kar rabim včeraj<br>\nje zreducirano na tvojo žejo<br>\nbolj kot izpijava<br>\nbolj izsušena usta imava<br>\nko se pustiva pred tvojimi vrati<br>\nko se taktično zavaruješ<br>\nker te za trenutek<br>\npostane strah svojih domnev in<br>\npričakovanj, ki jih nimam<br>\nin me pustiš čakati<br>\ns slanim okusom po obmorskih skalah<br>\ntaktično se zavarujem<br>\npričakovanj nikoli zares imel nisem<br>\nnamreč vem da<br>\npri tebi nikoli ne vem<br>\nkako se nit razvija</p>\n"
}