{
  "title": "wednesday villains",
  "meta": {
    "index": 1,
    "fileName": "2018-11-08-wednesday-villains.md",
    "section": "/raztemnenja",
    "dirName": "/articles"
  },
  "date": "2018-11-08",
  "path": "/raztemnenja/wednesday-villains",
  "permalink": "/raztemnenja/wednesday-villains",
  "anchors": [],
  "body": "<p>saturated digital hoarders<br>\nproducing that atp<br>\nchillin like we villains<br>\nin our categorical snuggies<br>\nwith em cheshire cat grins<br>\nspent and sold<br>\n<br>\nyoure a witch<br>\nim clairvoyant<br>\ni read your palm<br>\nthe veins of your leaves<br>\nthey pull me <br>\nand make naïve again</p>\n"
}